{
	"playlistName": "Aim Gods Easy",
	"scenarioList": [
		{
			"scenarioName": "Pokeball Frenzy Auto 1w4ts",
			"playCount": 3
		},
		{
			"scenarioName": "ww4t Varied",
			"playCount": 3
		},
		{
			"scenarioName": "Centering II 180 no strafes easier",
			"playCount": 3
		},
		{
			"scenarioName": "Ground Plaza Voltaic Invincible 2",
			"playCount": 2
		},
		{
			"scenarioName": "Ground Plaza Voltaic Invincible 3",
			"playCount": 2
		},
		{
			"scenarioName": "Thin Gauntlet 678",
			"playCount": 3
		},
		{
			"scenarioName": "Air no UFO no SKYBOTS Click",
			"playCount": 2
		},
		{
			"scenarioName": "Pole Long Dodge",
			"playCount": 3
		}
	],
	"isFavorite": false
}